{"users":[{"id":"user_69c07a875739e7.64202194","email":"ivandu259@gmail.com","password":"$2y$10$17kxrCWBU8uiqUrLGzwgn.a4dxQ4yKqVOcJeLLaA0Cy.wPuxHpEFG","createdAt":"2026-03-22 19:25:59"},{"id":"user_69c1b795a246c2.96355350","email":"ilias.spott3@gmail.com","password":"$2y$10$dBvzTcW.6P.zT9Siiu2vKOKBKnr.fZF59P5nH8nlHS5psoN.e5M16","createdAt":"2026-03-23 17:58:45"},{"id":"user_69c3ce8b3c6c20.37956000","email":"antonin.libson@outlook.com","password":"$2y$10$Pyl2P8XawoWAUUhWWTTBl.EH9zJJ80lJ950S4TNSubqGbT\/8ZgshO","createdAt":"2026-03-25 08:01:15"},{"id":"user_69c5bed49bca50.48309174","email":"shtonubbard@gmail.com","password":"$2y$10$zkvvzGaC.6tvkxtpi6FleOfQ3oeCriSIse6qYIf72Ss0mZOLhqaNO","createdAt":"2026-03-26 19:18:44"},{"id":"user_69c97d0b4c69a2.98585844","email":"Nniurza@gmail.com","password":"$2y$10$Fg2Lkuzfk2w0pLSwsehfF.xXTgaU1D8pluZ7GkjyGTXOf44qRkREq","createdAt":"2026-03-29 15:27:07"},{"id":"user_69ca0deadc62c1.74950764","email":"shudmell@gmail.com","password":"$2y$10$dkor9YWwPq.iTSoDy3DqxeYZY2wj8G83y.NZxyvC82W8FUvbKBcpC","createdAt":"2026-03-30 01:45:14"},{"id":"user_69cee413113024.64267291","email":"cenzodordain59@gmail.com","password":"$2y$10$K5nTi3HOhsTuKOdVVsjRp.2LPb4AO83iuP9f8YeD4whrumjHrBQLe","createdAt":"2026-04-02 17:48:03"},{"id":"user_69cee43912c016.22741274","email":"talkanoidop@gmail.com","password":"$2y$10$d4Qg2ihmDzoBnziNMyn4peg6DeoNiJa29F41FmZ7uSHlq3vpVVJFi","createdAt":"2026-04-02 17:48:41"}]}